aiosolaredge/__init__.py
aiosolaredge/py.typed
aiosolaredge/solaredge.py
aiosolaredge-0.2.0.dist-info/LICENSE
aiosolaredge-0.2.0.dist-info/METADATA
aiosolaredge-0.2.0.dist-info/WHEEL
aiosolaredge-0.2.0.dist-info/RECORD
