Metadata-Version: 2.1
Name: aiosolaredge
Version: 0.2.0
Summary: Asyncio SolarEdge
Home-page: https://github.com/bdraco/aiosolaredge
License: MIT
Author: J. Nick Koston
Author-email: nick@koston.org
Requires-Python: >=3.10,<4.0
Classifier: Development Status :: 2 - Pre-Alpha
Classifier: Intended Audience :: Developers
Classifier: License :: OSI Approved :: MIT License
Classifier: Natural Language :: English
Classifier: Operating System :: OS Independent
Classifier: Programming Language :: Python :: 3
Classifier: Programming Language :: Python :: 3.10
Classifier: Programming Language :: Python :: 3.11
Classifier: Programming Language :: Python :: 3.12
Classifier: Topic :: Software Development :: Libraries
Requires-Dist: aiohttp (>=3.9.0)
Requires-Dist: yarl (>=1.9.0)
Project-URL: Bug Tracker, https://github.com/bdraco/aiosolaredge/issues
Project-URL: Changelog, https://github.com/bdraco/aiosolaredge/blob/main/CHANGELOG.md
Project-URL: Documentation, https://aiosolaredge.readthedocs.io
Project-URL: Repository, https://github.com/bdraco/aiosolaredge
